setup.py
pickup/__init__.py
pickup/pickup.py
pickup.egg-info/PKG-INFO
pickup.egg-info/SOURCES.txt
pickup.egg-info/dependency_links.txt
pickup.egg-info/entry_points.txt
pickup.egg-info/requires.txt
pickup.egg-info/top_level.txt
pickup/config/__init__.py
pickup/generator_profile/__init__.py
pickup/generator_profile/command.py
pickup/generator_profile/folder.py
pickup/generator_profile/mysql.py
pickup/generator_profile/postgres.py
pickup/generator_profile/remote_tar.py
pickup/lib/__init__.py
pickup/lib/term.py
pickup/target_profile/__init__.py
pickup/target_profile/dailyfolder.py
pickup/target_profile/ftp.py