Metadata-Version: 1.0
Name: pickup
Version: 1.4
Summary: Modular backup script
Home-page: http://exhuma.github.com/pickup
Author: Michel Albert
Author-email: michel@albert.lu
License: BSD
Keywords: backup
Platform: UNKNOWN
